[
    {
        "subject_cat": "언매",
        "question_num": 1,
        "multiple_answer": 4
    },
    {
        "subject_cat": "언매",
        "question_num": 2,
        "multiple_answer": 4
    },
    {
        "subject_cat": "언매",
        "question_num": 3,
        "multiple_answer": 2
    },
    {
        "subject_cat": "언매",
        "question_num": 4,
        "multiple_answer": 5
    },
    {
        "subject_cat": "언매",
        "question_num": 5,
        "multiple_answer": 1
    },
    {
        "subject_cat": "언매",
        "question_num": 6,
        "multiple_answer": 4
    },
    {
        "subject_cat": "언매",
        "question_num": 7,
        "multiple_answer": 3
    },
    {
        "subject_cat": "언매",
        "question_num": 8,
        "multiple_answer": 4
    },
    {
        "subject_cat": "언매",
        "question_num": 9,
        "multiple_answer": 5
    },
    {
        "subject_cat": "언매",
        "question_num": 10,
        "multiple_answer": 2
    },
    {
        "subject_cat": "언매",
        "question_num": 11,
        "multiple_answer": 3
    },
    {
        "subject_cat": "언매",
        "question_num": 12,
        "multiple_answer": 4
    },
    {
        "subject_cat": "언매",
        "question_num": 13,
        "multiple_answer": 1
    },
    {
        "subject_cat": "언매",
        "question_num": 14,
        "multiple_answer": 5
    },
    {
        "subject_cat": "언매",
        "question_num": 15,
        "multiple_answer": 2
    },
    {
        "subject_cat": "언매",
        "question_num": 16,
        "multiple_answer": 2
    },
    {
        "subject_cat": "언매",
        "question_num": 17,
        "multiple_answer": 5
    },
    {
        "subject_cat": "언매",
        "question_num": 18,
        "multiple_answer": 1
    },
    {
        "subject_cat": "언매",
        "question_num": 19,
        "multiple_answer": 5
    },
    {
        "subject_cat": "언매",
        "question_num": 20,
        "multiple_answer": 3
    },
    {
        "subject_cat": "언매",
        "question_num": 21,
        "multiple_answer": 4
    },
    {
        "subject_cat": "언매",
        "question_num": 22,
        "multiple_answer": 1
    },
    {
        "subject_cat": "언매",
        "question_num": 23,
        "multiple_answer": 4
    },
    {
        "subject_cat": "언매",
        "question_num": 24,
        "multiple_answer": 3
    },
    {
        "subject_cat": "언매",
        "question_num": 25,
        "multiple_answer": 2
    },
    {
        "subject_cat": "언매",
        "question_num": 26,
        "multiple_answer": 1
    },
    {
        "subject_cat": "언매",
        "question_num": 27,
        "multiple_answer": 4
    },
    {
        "subject_cat": "언매",
        "question_num": 28,
        "multiple_answer": 2
    },
    {
        "subject_cat": "언매",
        "question_num": 29,
        "multiple_answer": 3
    },
    {
        "subject_cat": "언매",
        "question_num": 30,
        "multiple_answer": 1
    },
    {
        "subject_cat": "언매",
        "question_num": 31,
        "multiple_answer": 1
    },
    {
        "subject_cat": "언매",
        "question_num": 32,
        "multiple_answer": 3
    },
    {
        "subject_cat": "언매",
        "question_num": 33,
        "multiple_answer": 5
    },
    {
        "subject_cat": "언매",
        "question_num": 34,
        "multiple_answer": 2
    },
    {
        "subject_cat": "언매",
        "question_num": 35,
        "multiple_answer": 1
    },
    {
        "subject_cat": "언매",
        "question_num": 36,
        "multiple_answer": 4
    },
    {
        "subject_cat": "언매",
        "question_num": 37,
        "multiple_answer": 4
    },
    {
        "subject_cat": "언매",
        "question_num": 38,
        "multiple_answer": 5
    },
    {
        "subject_cat": "언매",
        "question_num": 39,
        "multiple_answer": 4
    },
    {
        "subject_cat": "언매",
        "question_num": 40,
        "multiple_answer": 1
    },
    {
        "subject_cat": "언매",
        "question_num": 41,
        "multiple_answer": 5
    },
    {
        "subject_cat": "언매",
        "question_num": 42,
        "multiple_answer": 5
    },
    {
        "subject_cat": "언매",
        "question_num": 43,
        "multiple_answer": 5
    },
    {
        "subject_cat": "언매",
        "question_num": 44,
        "multiple_answer": 2
    },
    {
        "subject_cat": "언매",
        "question_num": 45,
        "multiple_answer": 3
    }
]